kanchay/__init__.py
kanchay/kanchay.py
kanchay/kanchay_tools.py
kanchay-0.2.dist-info/LICENSE
kanchay-0.2.dist-info/METADATA
kanchay-0.2.dist-info/WHEEL
kanchay-0.2.dist-info/top_level.txt
kanchay-0.2.dist-info/RECORD
