Metadata-Version: 2.1
Name: kanchay
Version: 0.2
Summary: Tools based on lightkurve, starspot and exoplanet codes to measure rotational periods
Home-page: https://github.com/ramstojh/kanchay
Author: Jhon Yana
Author-email: ramstojh@alumni.usp.br
License: MIT
Platform: UNKNOWN
License-File: LICENSE
